click/__init__.py
click/_bashcomplete.py
click/_compat.py
click/_termui_impl.py
click/_textwrap.py
click/_unicodefun.py
click/_winconsole.py
click/core.py
click/decorators.py
click/exceptions.py
click/formatting.py
click/globals.py
click/parser.py
click/termui.py
click/testing.py
click/types.py
click/utils.py
plonecli_click-7.0.dev0.dist-info/DESCRIPTION.rst
plonecli_click-7.0.dev0.dist-info/LICENSE.txt
plonecli_click-7.0.dev0.dist-info/METADATA
plonecli_click-7.0.dev0.dist-info/RECORD
plonecli_click-7.0.dev0.dist-info/WHEEL
plonecli_click-7.0.dev0.dist-info/metadata.json
plonecli_click-7.0.dev0.dist-info/top_level.txt
