Metadata-Version: 2.0
Name: plonecli-click
Version: 7.0.dev0
Summary: A simple wrapper around optparse for powerful command line utilities.
Home-page: https://github.com/MrTango/click
Author: Maik Derstappen
Author-email: md@derico.de
License: UNKNOWN
Platform: UNKNOWN
Classifier: License :: OSI Approved :: BSD License
Classifier: Programming Language :: Python
Classifier: Programming Language :: Python :: 3
